voyager/__init__.py
voyager/ag-grid/ag-grid-community.min.js
voyager/ag-grid/bootstrap.min.css
voyager/ag-grid/data.js
voyager/ag-grid/index.html
voyager/ag-grid/main.js
voyager/ag-grid/styles.css
voyager/html/bundle.js
voyager/html/data.js
voyager/html/main.html
voyager/html/main.js
voyager/html/package-lock.json
voyager/html/package.json
voyager/html/style.css
voyager/html/font-awesome-4.7.0/HELP-US-OUT.txt
voyager/html/font-awesome-4.7.0/css/font-awesome.css
voyager/html/font-awesome-4.7.0/css/font-awesome.min.css
voyager/html/font-awesome-4.7.0/fonts/FontAwesome.otf
voyager/html/font-awesome-4.7.0/fonts/fontawesome-webfont.eot
voyager/html/font-awesome-4.7.0/fonts/fontawesome-webfont.svg
voyager/html/font-awesome-4.7.0/fonts/fontawesome-webfont.ttf
voyager/html/font-awesome-4.7.0/fonts/fontawesome-webfont.woff
voyager/html/font-awesome-4.7.0/fonts/fontawesome-webfont.woff2
voyager/html/font-awesome-4.7.0/less/animated.less
voyager/html/font-awesome-4.7.0/less/bordered-pulled.less
voyager/html/font-awesome-4.7.0/less/core.less
voyager/html/font-awesome-4.7.0/less/fixed-width.less
voyager/html/font-awesome-4.7.0/less/font-awesome.less
voyager/html/font-awesome-4.7.0/less/icons.less
voyager/html/font-awesome-4.7.0/less/larger.less
voyager/html/font-awesome-4.7.0/less/list.less
voyager/html/font-awesome-4.7.0/less/mixins.less
voyager/html/font-awesome-4.7.0/less/path.less
voyager/html/font-awesome-4.7.0/less/rotated-flipped.less
voyager/html/font-awesome-4.7.0/less/screen-reader.less
voyager/html/font-awesome-4.7.0/less/stacked.less
voyager/html/font-awesome-4.7.0/less/variables.less
voyager/html/font-awesome-4.7.0/scss/_animated.scss
voyager/html/font-awesome-4.7.0/scss/_bordered-pulled.scss
voyager/html/font-awesome-4.7.0/scss/_core.scss
voyager/html/font-awesome-4.7.0/scss/_fixed-width.scss
voyager/html/font-awesome-4.7.0/scss/_icons.scss
voyager/html/font-awesome-4.7.0/scss/_larger.scss
voyager/html/font-awesome-4.7.0/scss/_list.scss
voyager_launch-0.2.dist-info/LICENSE
voyager_launch-0.2.dist-info/METADATA
voyager_launch-0.2.dist-info/WHEEL
voyager_launch-0.2.dist-info/top_level.txt
voyager_launch-0.2.dist-info/RECORD
