Metadata-Version: 2.1
Name: voyager-launch
Version: 0.2
Summary: Open DataFrames in Voyager
Home-page: http://github.com/sswatson/voyager
Author: Samuel S. Watson
Author-email: samuel.s.watson@gmail.com
License: MIT
Platform: UNKNOWN
Requires-Dist: pandas
